README
setup.py
cronweasley/__init__.py
cronweasley/cronweasley.py
cronweasley.egg-info/PKG-INFO
cronweasley.egg-info/SOURCES.txt
cronweasley.egg-info/dependency_links.txt
cronweasley.egg-info/requires.txt
cronweasley.egg-info/top_level.txt
tests/test_jobs/__init__.py
tests/test_jobs/test1.py
tests/test_jobs/test2.py
tests/test_jobs/test3.py
tests/test_jobs/test4.py
tests/unit/__init__.py
tests/unit/test_example.py