Metadata-Version: 2.1
Name: cronweasley
Version: 1.4.3
Summary: Cronjobs for Wizards
Home-page: http://github.com/alairock/cron-weasley
Author: alairock
Author-email: sblnog@gmail.com
License: UNKNOWN
Keywords: cron crontab cronjob
Platform: UNKNOWN
Classifier: Development Status :: 4 - Beta
Classifier: Intended Audience :: Developers
Classifier: License :: OSI Approved :: MIT License
Classifier: Programming Language :: Python :: 3.5
Classifier: Programming Language :: Python :: 3.6
Provides-Extra: test
Provides-Extra: dev
